Metadata-Version: 2.1
Name: odoo-addon-purchase-order-hide-receipt-status
Version: 16.0.1.0.1.1
Summary: Purchase Order Hide Receipt Status
Home-page: https://github.com/OCA/purchase-workflow
Author: Quartile Limited, Odoo Community Association (OCA)
Author-email: support@odoo-community.org
License: AGPL-3
Platform: UNKNOWN
Classifier: Programming Language :: Python
Classifier: Framework :: Odoo
Classifier: Framework :: Odoo :: 16.0
Classifier: License :: OSI Approved :: GNU Affero General Public License v3
Requires-Python: >=3.10
Requires-Dist: odoo <16.1dev,>=16.0a
